[{"__symbolic":"module","version":3,"metadata":{},"exports":[{"from":"./column-selector-modal.component","export":["SkyColumnSelectorComponent"]},{"from":"./column-selector-context","export":["SkyColumnSelectorContext","SkyColumnSelectorModel"]},{"from":"./column-selector-modal.module","export":["SkyColumnSelectorModule"]}]},{"__symbolic":"module","version":1,"metadata":{},"exports":[{"from":"./column-selector-modal.component","export":["SkyColumnSelectorComponent"]},{"from":"./column-selector-context","export":["SkyColumnSelectorContext","SkyColumnSelectorModel"]},{"from":"./column-selector-modal.module","export":["SkyColumnSelectorModule"]}]}]